library360/__init__.py
library360/library.py
library360-0.1.0.dist-info/METADATA
library360-0.1.0.dist-info/WHEEL
library360-0.1.0.dist-info/top_level.txt
library360-0.1.0.dist-info/RECORD
